pylimiter/__init__.py
pylimiter/limiter.py
pylimiter/backend/__init__.py
pylimiter/backend/default.py
pylimiter/backend/interface.py
pylimiter-0.2.0.dist-info/LICENSE.md
pylimiter-0.2.0.dist-info/METADATA
pylimiter-0.2.0.dist-info/WHEEL
pylimiter-0.2.0.dist-info/top_level.txt
pylimiter-0.2.0.dist-info/RECORD
