Metadata-Version: 2.1
Name: pylimiter
Version: 0.2.0
Summary: Limiter Python SDK
Home-page: https://github.com/microrg/py-limiter
Author: Limiter
Author-email: support@applimiter.com
Project-URL: Bug Tracker, https://github.com/microrg/py-limiter/issues
Classifier: Programming Language :: Python :: 3
Classifier: License :: OSI Approved :: MIT License
Classifier: Operating System :: OS Independent
Requires-Python: >=3.6
License-File: LICENSE.md
